nexis_uni_parser/__init__.py
nexis_uni_parser/__main__.py
nexis_uni_parser/cli.py
nexis_uni_parser/parser.py
nexis_uni_parser/py.typed
nexis_uni_parser-0.1.5.dist-info/entry_points.txt
nexis_uni_parser-0.1.5.dist-info/LICENSE
nexis_uni_parser-0.1.5.dist-info/WHEEL
nexis_uni_parser-0.1.5.dist-info/METADATA
nexis_uni_parser-0.1.5.dist-info/RECORD
