Metadata-Version: 2.1
Name: nexis-uni-parser
Version: 0.1.5
Summary: Parse NexisUni rtf files into a jsonlines file.
Home-page: https://github.com/garth74/nexis-uni-parser
License: MIT
Author: Garrett M. Shipley
Author-email: garrett.shipley7@gmail.com
Requires-Python: >=3.7,<4.0
Classifier: Development Status :: 4 - Beta
Classifier: License :: OSI Approved :: MIT License
Classifier: Programming Language :: Python :: 3
Classifier: Programming Language :: Python :: 3.10
Classifier: Programming Language :: Python :: 3.7
Classifier: Programming Language :: Python :: 3.8
Classifier: Programming Language :: Python :: 3.9
Requires-Dist: Unidecode (>=1.3.4,<2.0.0)
Requires-Dist: click (>=8.0.1)
Requires-Dist: typer (>=0.6.1,<0.7.0)
Project-URL: Changelog, https://github.com/garth74/nexis-uni-parser/releases
Project-URL: Documentation, https://nexis-uni-parser.readthedocs.io
Project-URL: Repository, https://github.com/garth74/nexis-uni-parser
